{
  "code_of_conduct_url": null,
  "contributions_count": 3,
  "contribution_guidelines_url": null,
  "dependent_repos_count": 2,
  "dependents_count": 3,
  "deprecation_reason": null,
  "description": "Tasks is a wrapper around gulp for most of the use cases for simple and modern (frontend) web development ",
  "forks": 0,
  "funding_urls": [],
  "homepage": "https://github.com/webtides/tasks#readme",
  "keywords": [
    "tasks",
    "frontend tasks",
    "gulp",
    "gulp tasks",
    "frontend",
    "rollup",
    "postcss",
    "svg sprite"
  ],
  "language": "JavaScript",
  "latest_download_url": "https://registry.npmjs.org/@webtides/tasks/-/@webtides/tasks-1.0.0.tgz",
  "latest_release_number": "1.0.0",
  "latest_release_published_at": "2024-06-14T12:21:30.641Z",
  "latest_stable_release_number": "1.0.0",
  "latest_stable_release_published_at": "2024-06-14T12:21:30.641Z",
  "license_normalized": false,
  "licenses": "MIT",
  "name": "@webtides/tasks",
  "normalized_licenses": [
    "MIT"
  ],
  "package_manager_url": "https://www.npmjs.com/package/@webtides/tasks",
  "platform": "NPM",
  "rank": 8,
  "repository_license": "MIT",
  "repository_status": null,
  "repository_url": "https://github.com/webtides/tasks",
  "security_policy_url": null,
  "stars": 2,
  "status": null,
  "versions": [
    {
      "number": "0.3.0",
      "published_at": "2021-03-11T19:34:11.852Z",
      "spdx_expression": "MIT",
      "original_license": "MIT",
      "researched_at": null,
      "repository_sources": [
        "NPM"
      ]
    },
    {
      "number": "0.4.0",
      "published_at": "2021-03-31T09:09:20.662Z",
      "spdx_expression": "MIT",
      "original_license": "MIT",
      "researched_at": null,
      "repository_sources": [
        "NPM"
      ]
    },
    {
      "number": "0.4.0-0.1",
      "published_at": "2021-03-29T09:23:53.466Z",
      "spdx_expression": "MIT",
      "original_license": "MIT",
      "researched_at": null,
      "repository_sources": [
        "NPM"
      ]
    },
    {
      "number": "0.4.0-rc.1",
      "published_at": "2021-03-11T20:30:31.517Z",
      "spdx_expression": "MIT",
      "original_license": "MIT",
      "researched_at": null,
      "repository_sources": [
        "NPM"
      ]
    },
    {
      "number": "0.5.0",
      "published_at": "2021-04-14T16:15:18.417Z",
      "spdx_expression": "MIT",
      "original_license": "MIT",
      "researched_at": null,
      "repository_sources": [
        "NPM"
      ]
    },
    {
      "number": "0.5.1",
      "published_at": "2021-05-04T09:12:09.108Z",
      "spdx_expression": "MIT",
      "original_license": "MIT",
      "researched_at": null,
      "repository_sources": [
        "NPM"
      ]
    },
    {
      "number": "0.5.2",
      "published_at": "2021-05-05T09:14:12.348Z",
      "spdx_expression": "MIT",
      "original_license": "MIT",
      "researched_at": null,
      "repository_sources": [
        "NPM"
      ]
    },
    {
      "number": "0.5.3",
      "published_at": "2021-05-11T10:00:04.610Z",
      "spdx_expression": "MIT",
      "original_license": "MIT",
      "researched_at": null,
      "repository_sources": [
        "NPM"
      ]
    },
    {
      "number": "0.5.4",
      "published_at": "2021-05-11T12:01:50.407Z",
      "spdx_expression": "MIT",
      "original_license": "MIT",
      "researched_at": null,
      "repository_sources": [
        "NPM"
      ]
    },
    {
      "number": "0.6.0",
      "published_at": "2022-01-19T11:24:52.303Z",
      "spdx_expression": "MIT",
      "original_license": "MIT",
      "researched_at": null,
      "repository_sources": [
        "NPM"
      ]
    },
    {
      "number": "1.0.0",
      "published_at": "2024-06-14T12:21:30.641Z",
      "spdx_expression": "MIT",
      "original_license": "MIT",
      "researched_at": null,
      "repository_sources": [
        "NPM"
      ]
    }
  ]
}