{
  "code_of_conduct_url": "https://github.com/CoLRev-Environment/colrev/blob/main/CODE_OF_CONDUCT.md",
  "contributions_count": 34,
  "contribution_guidelines_url": "https://github.com/CoLRev-Environment/colrev/blob/main/CONTRIBUTING.md",
  "dependent_repos_count": 1,
  "dependents_count": 2,
  "deprecation_reason": null,
  "description": "CoLRev: An open-source environment for collaborative reviews",
  "forks": 24,
  "funding_urls": [],
  "homepage": "https://colrev-environment.github.io/colrev/",
  "keywords": [
    "research",
    "reproducible",
    "open",
    "science",
    "literature",
    "review",
    "systematic",
    "open-science",
    "openscience",
    "reproducible-research",
    "systematic-literature-review",
    "systematic-review"
  ],
  "language": "Python",
  "latest_download_url": null,
  "latest_release_number": "0.13.1",
  "latest_release_published_at": "2024-12-17T09:45:09.000Z",
  "latest_stable_release_number": "0.13.1",
  "latest_stable_release_published_at": "2024-12-17T09:45:09.000Z",
  "license_normalized": false,
  "licenses": "MIT",
  "name": "colrev",
  "normalized_licenses": [
    "MIT"
  ],
  "package_manager_url": "https://pypi.org/project/colrev/",
  "platform": "Pypi",
  "rank": 9,
  "repository_license": "MIT",
  "repository_status": null,
  "repository_url": "https://github.com/CoLRev-Environment/colrev",
  "security_policy_url": "https://github.com/CoLRev-Environment/colrev/security/policy",
  "stars": 29,
  "status": null,
  "versions": [
    {
      "number": "0.0.1",
      "published_at": "2022-03-10T06:39:12.000Z",
      "spdx_expression": "NONE",
      "original_license": "",
      "researched_at": null,
      "repository_sources": [
        "Pypi"
      ]
    },
    {
      "number": "0.10.0",
      "published_at": "2023-10-02T07:17:28.000Z",
      "spdx_expression": "MIT",
      "original_license": "MIT",
      "researched_at": null,
      "repository_sources": [
        "Pypi"
      ]
    },
    {
      "number": "0.10.1",
      "published_at": "2023-10-06T13:06:45.000Z",
      "spdx_expression": "MIT",
      "original_license": "MIT",
      "researched_at": null,
      "repository_sources": [
        "Pypi"
      ]
    },
    {
      "number": "0.10.2",
      "published_at": "2023-10-15T12:08:37.000Z",
      "spdx_expression": "MIT",
      "original_license": "MIT",
      "researched_at": null,
      "repository_sources": [
        "Pypi"
      ]
    },
    {
      "number": "0.10.3",
      "published_at": "2023-10-25T05:16:55.000Z",
      "spdx_expression": "MIT",
      "original_license": "MIT",
      "researched_at": null,
      "repository_sources": [
        "Pypi"
      ]
    },
    {
      "number": "0.10.4",
      "published_at": "2023-10-25T05:53:50.000Z",
      "spdx_expression": "MIT",
      "original_license": "MIT",
      "researched_at": null,
      "repository_sources": [
        "Pypi"
      ]
    },
    {
      "number": "0.11.0",
      "published_at": "2024-02-17T20:49:03.000Z",
      "spdx_expression": "MIT",
      "original_license": "MIT",
      "researched_at": null,
      "repository_sources": [
        "Pypi"
      ]
    },
    {
      "number": "0.12.0",
      "published_at": "2024-04-04T16:45:29.000Z",
      "spdx_expression": "MIT",
      "original_license": "MIT",
      "researched_at": null,
      "repository_sources": [
        "Pypi"
      ]
    },
    {
      "number": "0.12.1",
      "published_at": "2024-04-17T07:32:57.000Z",
      "spdx_expression": "MIT",
      "original_license": "MIT",
      "researched_at": null,
      "repository_sources": [
        "Pypi"
      ]
    },
    {
      "number": "0.12.2",
      "published_at": "2024-04-29T08:17:20.000Z",
      "spdx_expression": "MIT",
      "original_license": "MIT",
      "researched_at": null,
      "repository_sources": [
        "Pypi"
      ]
    },
    {
      "number": "0.12.3",
      "published_at": "2024-06-15T09:58:04.000Z",
      "spdx_expression": "MIT",
      "original_license": "MIT",
      "researched_at": null,
      "repository_sources": [
        "Pypi"
      ]
    },
    {
      "number": "0.13.0",
      "published_at": "2024-10-04T09:15:07.000Z",
      "spdx_expression": "MIT",
      "original_license": "MIT",
      "researched_at": null,
      "repository_sources": [
        "Pypi"
      ]
    },
    {
      "number": "0.13.1",
      "published_at": "2024-12-17T09:45:09.000Z",
      "spdx_expression": "MIT",
      "original_license": "MIT",
      "researched_at": null,
      "repository_sources": [
        "Pypi"
      ]
    },
    {
      "number": "0.7.0",
      "published_at": "2023-02-02T20:29:00.869Z",
      "spdx_expression": "MIT",
      "original_license": "MIT",
      "researched_at": null,
      "repository_sources": [
        "Pypi"
      ]
    },
    {
      "number": "0.7.1",
      "published_at": "2023-03-08T07:42:01.126Z",
      "spdx_expression": "MIT",
      "original_license": "MIT",
      "researched_at": null,
      "repository_sources": [
        "Pypi"
      ]
    },
    {
      "number": "0.8.0",
      "published_at": "2023-03-26T15:28:00.501Z",
      "spdx_expression": "MIT",
      "original_license": "MIT",
      "researched_at": null,
      "repository_sources": [
        "Pypi"
      ]
    },
    {
      "number": "0.8.1",
      "published_at": "2023-04-04T12:50:02.794Z",
      "spdx_expression": "MIT",
      "original_license": "MIT",
      "researched_at": null,
      "repository_sources": [
        "Pypi"
      ]
    },
    {
      "number": "0.8.2",
      "published_at": "2023-04-05T07:23:03.699Z",
      "spdx_expression": "MIT",
      "original_license": "MIT",
      "researched_at": null,
      "repository_sources": [
        "Pypi"
      ]
    },
    {
      "number": "0.8.3",
      "published_at": "2023-04-23T07:22:09.022Z",
      "spdx_expression": "MIT",
      "original_license": "MIT",
      "researched_at": null,
      "repository_sources": [
        "Pypi"
      ]
    },
    {
      "number": "0.8.4",
      "published_at": "2023-05-19T10:47:00.550Z",
      "spdx_expression": "MIT",
      "original_license": "MIT",
      "researched_at": null,
      "repository_sources": [
        "Pypi"
      ]
    },
    {
      "number": "0.9.0",
      "published_at": "2023-05-31T20:25:00.403Z",
      "spdx_expression": "MIT",
      "original_license": "MIT",
      "researched_at": null,
      "repository_sources": [
        "Pypi"
      ]
    },
    {
      "number": "0.9.2",
      "published_at": "2023-07-24T05:33:58.000Z",
      "spdx_expression": "MIT",
      "original_license": "MIT",
      "researched_at": null,
      "repository_sources": [
        "Pypi"
      ]
    },
    {
      "number": "0.9.3",
      "published_at": "2023-10-01T19:11:34.000Z",
      "spdx_expression": "MIT",
      "original_license": "MIT",
      "researched_at": null,
      "repository_sources": [
        "Pypi"
      ]
    }
  ]
}