{
  "code_of_conduct_url": null,
  "contributions_count": 20,
  "contribution_guidelines_url": null,
  "dependent_repos_count": 0,
  "dependents_count": 0,
  "deprecation_reason": null,
  "description": "Package that defines common interfaces for workflows that are implemented in AiiDA for various quantum engines.",
  "forks": 26,
  "funding_urls": [],
  "homepage": "https://github.com/aiidateam/aiida-common-workflows",
  "keywords": [
    "aiida",
    "workflows",
    "common-workflows",
    "dft"
  ],
  "language": "Python",
  "latest_download_url": null,
  "latest_release_number": "1.0.1",
  "latest_release_published_at": "2023-09-16T12:34:26.000Z",
  "latest_stable_release_number": "1.0.1",
  "latest_stable_release_published_at": "2023-09-16T12:34:26.000Z",
  "license_normalized": true,
  "licenses": "MIT License",
  "name": "aiida-common-workflows",
  "normalized_licenses": [
    "MIT"
  ],
  "package_manager_url": "https://pypi.org/project/aiida-common-workflows/",
  "platform": "Pypi",
  "rank": 11,
  "repository_license": "MIT",
  "repository_status": null,
  "repository_url": "https://github.com/aiidateam/aiida-common-workflows",
  "security_policy_url": null,
  "stars": 41,
  "status": null,
  "versions": [
    {
      "number": "0.1.0",
      "published_at": "2021-04-28T11:54:30.000Z",
      "spdx_expression": "NOASSERTION",
      "original_license": "MIT License",
      "researched_at": null,
      "repository_sources": [
        "Pypi"
      ]
    },
    {
      "number": "1.0.0",
      "published_at": "2023-09-10T12:27:15.000Z",
      "spdx_expression": null,
      "original_license": null,
      "researched_at": null,
      "repository_sources": [
        "Pypi"
      ]
    },
    {
      "number": "1.0.1",
      "published_at": "2023-09-16T12:34:26.000Z",
      "spdx_expression": null,
      "original_license": null,
      "researched_at": null,
      "repository_sources": [
        "Pypi"
      ]
    }
  ]
}